doc_store/__init__.py
doc_store/base_routes.py
doc_store/config.py
doc_store/doc_client.py
doc_store/doc_server.py
doc_store/doc_store.py
doc_store/doris_db.py
doc_store/drawing.py
doc_store/drawing_font.ttf
doc_store/es.py
doc_store/interface.py
doc_store/io.py
doc_store/json_util.py
doc_store/kafka.py
doc_store/mongodb.py
doc_store/oid.py
doc_store/pdf_doc.py
doc_store/redis_stream.py
doc_store/s3.py
doc_store/server_app.py
doc_store/structs.py
doc_store/utils.py
doc_store/version.py
doc_store-0.7.1.dist-info/licenses/LICENSE.md
doc_store-0.7.1.dist-info/METADATA
doc_store-0.7.1.dist-info/WHEEL
doc_store-0.7.1.dist-info/top_level.txt
doc_store-0.7.1.dist-info/RECORD
